obvs/__init__.py
obvs/lenses.py
obvs/logging.py
obvs/metrics.py
obvs/patchscope.py
obvs/patchscope_base.py
obvs/vis.py
obvs-0.1.2.dist-info/LICENSE
obvs-0.1.2.dist-info/METADATA
obvs-0.1.2.dist-info/WHEEL
obvs-0.1.2.dist-info/RECORD
